lambda_kit/__init__.py
lambda_kit/__main__.py
lambda_kit/mvc/__init__.py
lambda_kit/mvc/controllers/__init__.py
lambda_kit/mvc/controllers/function_controller.py
lambda_kit/mvc/controllers/layer_controller.py
lambda_kit/mvc/models/__init__.py
lambda_kit/mvc/models/function_model.py
lambda_kit/mvc/models/layer_model.py
lambda_kit/mvc/views/__init__.py
lambda_kit/mvc/views/base_view.py
lambda_kit/mvc/views/function_view.py
lambda_kit/mvc/views/layer_view.py
lambda_kit/utils/__init__.py
lambda_kit/utils/aws_lambda.py
lambda_kit/utils/directory.py
lambda_kit/utils/file.py
lambda_kit/utils/logger.py
lambda_kit-1.0.14.dist-info/LICENSE
lambda_kit-1.0.14.dist-info/METADATA
lambda_kit-1.0.14.dist-info/WHEEL
lambda_kit-1.0.14.dist-info/entry_points.txt
lambda_kit-1.0.14.dist-info/top_level.txt
lambda_kit-1.0.14.dist-info/RECORD
