Metadata-Version: 2.1
Name: lambda-kit
Version: 1.0.14
Summary: A tool to package Python code for AWS Lambda.
Author: Omar Crosby
Author-email: Omar Crosby <omar.crosby@gmail.com>
License: MIT License
Project-URL: homepage, https://github.com/ocrosby/lambda-kit
Keywords: aws,lambda,packaging,deployment
Classifier: Development Status :: 4 - Beta
Classifier: Intended Audience :: Developers
Classifier: License :: OSI Approved :: MIT License
Classifier: Programming Language :: Python :: 3
Classifier: Programming Language :: Python :: 3.12
Requires-Python: >=3.9
License-File: LICENSE
Requires-Dist: click
Requires-Dist: requests
Requires-Dist: Jinja2
Requires-Dist: pydantic
Requires-Dist: aws-lambda-typing
Requires-Dist: toml
Provides-Extra: dev
Requires-Dist: black ; extra == 'dev'
Requires-Dist: flake8 ; extra == 'dev'
Requires-Dist: mypy ; extra == 'dev'
Requires-Dist: isort ; extra == 'dev'
Requires-Dist: pylint ; extra == 'dev'
Requires-Dist: pytest ; extra == 'dev'
Requires-Dist: pytest-cov ; extra == 'dev'
Requires-Dist: pytest-mock ; extra == 'dev'
Requires-Dist: pytest-xdist ; extra == 'dev'
Requires-Dist: invoke ; extra == 'dev'
Requires-Dist: radon ; extra == 'dev'
Requires-Dist: tox ; extra == 'dev'
Requires-Dist: coverage ; extra == 'dev'
Requires-Dist: coveralls ; extra == 'dev'
